LICENSE
MANIFEST.in
README.md
__init__.py
setup.cfg
setup.py
configproxy/__init__.py
configproxy.egg-info/PKG-INFO
configproxy.egg-info/SOURCES.txt
configproxy.egg-info/dependency_links.txt
configproxy.egg-info/requires.txt
configproxy.egg-info/top_level.txt