Metadata-Version: 1.0
Name: configproxy
Version: 0.0.3
Summary: Binding to jupyter configurable-http-proxy
Home-page: https://github.com/joequant/configproxy
Author: Joseph C Wang
Author-email: joequant@gmail.com
License: BSD
Platform: UNKNOWN
